archivista/__init__.py
archivista/archivista.py
archivista/config/__init__.py
archivista/config/config.py
archivista/seccion_breadcrumb/__init__.py
archivista/seccion_breadcrumb/seccion_breadcrumb.py
archivista/seccion_descargables/__init__.py
archivista/seccion_descargables/descargable.py
archivista/seccion_descargables/seccion_descargables.py
archivista/seccion_final/__init__.py
archivista/seccion_final/archivo_md.py
archivista/seccion_final/seccion_final.py
archivista/seccion_inicial/__init__.py
archivista/seccion_inicial/archivo_md_inicial.py
archivista/seccion_inicial/indice.py
archivista/seccion_inicial/seccion_inicial.py
archivista/seccion_subdirectorios/__init__.py
archivista/seccion_subdirectorios/descargable.py
archivista/seccion_subdirectorios/seccion_subdirectorios.py
archivista/seccion_subdirectorios/subdirectorio.py
archivista/seccion_subdirectorios/vinculo_relativo.py
archivista/universales/__init__.py
archivista/universales/base.py
archivista/universales/funciones.py
archivista/universales/pagina.py
archivista/universales/rama.py
archivista-0.4.6.dist-info/LICENSE
archivista-0.4.6.dist-info/METADATA
archivista-0.4.6.dist-info/WHEEL
archivista-0.4.6.dist-info/entry_points.txt
archivista-0.4.6.dist-info/top_level.txt
archivista-0.4.6.dist-info/RECORD
