Metadata-Version: 2.1
Name: archivista
Version: 0.4.6
Summary: Transformador de contenidos para Pelican
Home-page: https://github.com/guivaloz/archivista
Author: Guillermo Valdes Lozano
Author-email: guillermo@movimientolibre.com
Classifier: Programming Language :: Python :: 3
Classifier: License :: OSI Approved :: GNU Affero General Public License v3 or later (AGPLv3+)
Classifier: Operating System :: POSIX :: Linux
Requires-Python: >=3.6
License-File: LICENSE
Requires-Dist: click
Requires-Dist: Jinja2
Requires-Dist: Markdown
